{
"employees": [

{

"index": 1,
"age": 37,
"rate": 14.9436,
"name": "Nina",
"surname": "Underwood",
"fullname": "Hilda Barton",
"email": "sheryl@marks.org",
"paid": true
},
{

"index": 2,
"age": 25,
"rate": 11.1002,
"name": "Zachary",
"surname": "Dunn",
"fullname": "Nina Godfrey",
"email": "lauren@puckett.to",
"paid": true
},
{

"index": 3,
"age": 48,
"rate": 19.8686,
"name": "Alex",
"surname": "Holmes",
"fullname": "Frances Duke",
"email": "rhonda@sinclair.lu",
"paid": false
},
{

"index": 4,
"age": 25,
"rate": 15.0839,
"name": "Keith",
"surname": "Blackburn",
"fullname": "Stacey Koch",
"email": "ben@cox.es",
"paid": true
},
{

"index": 5,
"age": 15,
"rate": 14.7735,
"name": "Eleanor",
"surname": "Lucas",
"fullname": "Paul Bowden",
"email": "laura@chan.lt",
"paid": false
},
{

"index": 6,
"age": 30,
"rate": 16.186,
"name": "Beth",
"surname": "Carter",
"fullname": "Sandra Holden",
"email": "sara@hardison.aw",
"paid": false
},
{

"index": 7,
"age": 7,
"rate": 12.2562,
"name": "Franklin",
"surname": "Wall",
"fullname": "Annie Bowers",
"email": "julian@chase.bf",
"paid": false
},
{

"index": 8,
"age": 11,
"rate": 12.1374,
"name": "Frederick",
"surname": "Pickett",
"fullname": "Kristine Garrett",
"email": "hazel@beatty.vg",
"paid": false
},
{

"index": 9,
"age": 42,
"rate": 13.4315,
"name": "Sarah",
"surname": "Underwood",
"fullname": "George Schultz",
"email": "barbara@wagner.gd",
"paid": false
},
{

"index": 10,
"age": 48,
"rate": 16.9727,
"name": "Wade",
"surname": "Reid",
"fullname": "Elsie Dodson",
"email": "tracey@hicks.ms",
"paid": true
}
]
}